langflow/version/__init__.py
langflow/version/version.py
langflow_nightly-1.8.0.dev35.dist-info/METADATA
langflow_nightly-1.8.0.dev35.dist-info/WHEEL
langflow_nightly-1.8.0.dev35.dist-info/entry_points.txt
langflow_nightly-1.8.0.dev35.dist-info/licenses/LICENSE
langflow_nightly-1.8.0.dev35.dist-info/RECORD
