Metadata-Version: 2.4
Name: langflow-nightly
Version: 1.8.0.dev35
Summary: A Python package with a built-in web application
Project-URL: Repository, https://github.com/langflow-ai/langflow
Project-URL: Documentation, https://docs.langflow.org
Maintainer-email: Carlos Coelho <carlos@langflow.org>, Cristhian Zanforlin <cristhian.lousa@gmail.com>, Gabriel Almeida <gabriel@langflow.org>, Lucas Eduoli <lucaseduoli@gmail.com>, Otávio Anovazzi <otavio2204@gmail.com>, Rodrigo Nader <rodrigo@langflow.org>, Italo dos Anjos <italojohnnydosanjos@gmail.com>
License-Expression: MIT
License-File: LICENSE
Keywords: gpt,gui,langchain,nlp,openai
Requires-Python: <3.14,>=3.10
Requires-Dist: langflow-base-nightly[complete]==1.8.0.dev35
Provides-Extra: audio
Requires-Dist: webrtcvad>=2.0.10; extra == 'audio'
Provides-Extra: cassio
Requires-Dist: cassio>=0.1.7; extra == 'cassio'
Provides-Extra: clickhouse-connect
Requires-Dist: clickhouse-connect==0.7.19; extra == 'clickhouse-connect'
Provides-Extra: couchbase
Requires-Dist: couchbase>=4.2.1; extra == 'couchbase'
Provides-Extra: docling
Requires-Dist: langchain-docling>=1.1.0; extra == 'docling'
Requires-Dist: ocrmac>=1.0.0; (sys_platform == 'darwin') and extra == 'docling'
Requires-Dist: rapidocr-onnxruntime>=1.4.4; extra == 'docling'
Requires-Dist: tesserocr>=2.8.0; extra == 'docling'
Provides-Extra: local
Requires-Dist: ctransformers>=0.2.10; extra == 'local'
Requires-Dist: llama-cpp-python~=0.2.0; extra == 'local'
Requires-Dist: sentence-transformers>=2.3.1; extra == 'local'
Provides-Extra: nv-ingest
Requires-Dist: nv-ingest-api<26.0.0,==25.6.2; (python_version >= '3.12') and extra == 'nv-ingest'
Requires-Dist: nv-ingest-client<26.0.0,==25.6.3; (python_version >= '3.12') and extra == 'nv-ingest'
Provides-Extra: postgresql
Requires-Dist: sqlalchemy[postgresql-psycopg2binary]<3.0.0,>=2.0.38; extra == 'postgresql'
Requires-Dist: sqlalchemy[postgresql-psycopg]<3.0.0,>=2.0.38; extra == 'postgresql'
